MANIFEST.in
README.md
VERSION
requirements.txt
setup.cfg
setup.py
construi/__init__.py
construi/__version__.py
construi/cli.py
construi/config.py
construi/console.py
construi/errors.py
construi/target.py
construi.egg-info/PKG-INFO
construi.egg-info/SOURCES.txt
construi.egg-info/dependency_links.txt
construi.egg-info/entry_points.txt
construi.egg-info/requires.txt
construi.egg-info/top_level.txt
construi.egg-info/zip-safe
test/test_config.py
test/test_sanity.py